[  {    "abreviatura": "ISC",    "nombre_largo": "Ingeniería en Sistemas Computacionales",    "departamento": "Ingeniería"  },  {    "abreviatura": "ADM",    "nombre_largo": "Administración de Empresas",    "departamento": "Negocios"  },  {    "abreviatura": "PSIC",    "nombre_largo": "Psicología",    "departamento": "Humanidades"  },  {    "abreviatura": "ARQ",    "nombre_largo": "Arquitectura",    "departamento": "Ingeniería"  },  {    "abreviatura": "DER",    "nombre_largo": "Derecho",    "departamento": "Humanidades"  },  {    "abreviatura": "MEDI",    "nombre_largo": "Medicina",    "departamento": "Salud"  },  {    "abreviatura": "FIN",    "nombre_largo": "Finanzas",    "departamento": "Negocios"  },  {    "abreviatura": "CIV",    "nombre_largo": "Ingeniería Civil",    "departamento": "Ingeniería"  },  {    "abreviatura": "ART",    "nombre_largo": "Artes Visuales",    "departamento": "Humanidades"  },  {    "abreviatura": "BIO",    "nombre_largo": "Biología",    "departamento": "Salud"  }]
